
{"items":[{"name":"Tutorials & Info"},{"name":"Local Documentation","href":"tutorials-info/generating-docs.html","topicHref":"tutorials-info/generating-docs.html"},{"name":"Workflow","href":"tutorials-info/workflow.html","topicHref":"tutorials-info/workflow.html"},{"name":"Major Settings Changes","href":"tutorials-info/major-settings-changes.html","topicHref":"tutorials-info/major-settings-changes.html"},{"name":"Manuals"},{"name":"System Architecture","href":"manuals/system-architecture.html","topicHref":"manuals/system-architecture.html"},{"name":"Custom Input","href":"manuals/cinput-manual.html","topicHref":"manuals/cinput-manual.html"}]}
